mathai/__init__.py
mathai/apart.py
mathai/base.py
mathai/bivariate_inequality.py
mathai/console.py
mathai/diff.py
mathai/expand.py
mathai/factor.py
mathai/fraction.py
mathai/integrate.py
mathai/inverse.py
mathai/limit.py
mathai/linear.py
mathai/logic.py
mathai/matrix.py
mathai/ode.py
mathai/parser.py
mathai/parsetab.py
mathai/pde.py
mathai/printeq.py
mathai/simplify.py
mathai/statistics.py
mathai/structure.py
mathai/tool.py
mathai/trig.py
mathai/univariate_inequality.py
mathai-0.7.8.dist-info/METADATA
mathai-0.7.8.dist-info/WHEEL
mathai-0.7.8.dist-info/top_level.txt
mathai-0.7.8.dist-info/RECORD
