Metadata-Version: 2.4
Name: mathai
Version: 0.7.8
Summary: Mathematics solving Ai tailored to NCERT
Home-page: https://github.com/infinity390/mathai4
Requires-Python: >=3.7
Requires-Dist: lark-parser
Dynamic: description
Dynamic: description-content-type
Dynamic: home-page
Dynamic: requires-dist
Dynamic: requires-python
Dynamic: summary
